[{"questionText":"What is the primary purpose of Google Kubernetes Engine (GKE)?","type":"","category":"gcp","subcategory":"gke","dateadded":"11-November-2025","certification":"","answerReference":"Managing containerized applications on Google Cloud.","answers":[{"text":"Running virtual machines on Google Cloud.","iscorrect":false},{"text":"Managing containerized applications on Google Cloud.","iscorrect":true},{"text":"Storing large amounts of data in the cloud.","iscorrect":false},{"text":"Providing serverless functions on Google Cloud.","iscorrect":false}]},{"questionText":"What is a Node Pool in GKE?","type":"","category":"gcp","subcategory":"gke","dateadded":"11-November-2025","certification":"","answerReference":"A group of nodes within a GKE cluster that all have the same configuration.","answers":[{"text":"A group of pods that are always scheduled together.","iscorrect":false},{"text":"A configuration file that defines the cluster's network.","iscorrect":false},{"text":"A group of nodes within a GKE cluster that all have the same configuration.","iscorrect":true},{"text":"A service that automatically scales the number of nodes.","iscorrect":false}]},{"questionText":"What is Cluster Autoscaler in GKE?","type":"","category":"gcp","subcategory":"gke","dateadded":"11-November-2025","certification":"","answerReference":"A feature that automatically adjusts the number of nodes in a node pool based on resource requests.","answers":[{"text":"A feature that automatically scales the number of pods in a deployment.","iscorrect":false},{"text":"A feature that automatically adjusts the number of nodes in a node pool based on resource requests.","iscorrect":true},{"text":"A feature that automatically restarts failed pods.","iscorrect":false},{"text":"A feature that automatically distributes network traffic across pods.","iscorrect":false}]},{"questionText":"What is Horizontal Pod Autoscaler (HPA) in GKE?","type":"","category":"gcp","subcategory":"gke","dateadded":"11-November-2025","certification":"","answerReference":"A Kubernetes feature that automatically scales the number of pod replicas in a deployment based on observed metrics.","answers":[{"text":"Automatically scales the number of nodes in a node pool.","iscorrect":false},{"text":"Automatically scales the number of pods in a deployment based on observed metrics.","iscorrect":true},{"text":"Automatically restarts failed pods.","iscorrect":false},{"text":"Automatically distributes network traffic across pods.","iscorrect":false}]},{"questionText":"What is Vertical Pod Autoscaler (VPA) in GKE?","type":"","category":"gcp","subcategory":"gke","dateadded":"11-November-2025","certification":"","answerReference":"Automatically adjusts the CPU and memory resource requests of containers in pods.","answers":[{"text":"Automatically scales the number of pods in a deployment.","iscorrect":false},{"text":"Automatically adjusts the CPU and memory resource requests of containers in pods.","iscorrect":true},{"text":"Automatically scales the number of nodes in a node pool.","iscorrect":false},{"text":"Automatically distributes network traffic across pods.","iscorrect":false}]},{"questionText":"What is a StatefulSet in Kubernetes?","type":"","category":"gcp","subcategory":"gke","dateadded":"11-November-2025","certification":"","answerReference":"A controller that manages stateful applications, providing stable network identifiers and persistent storage.","answers":[{"text":"A controller for stateless applications.","iscorrect":false},{"text":"A controller that manages stateful applications, providing stable network identifiers and persistent storage.","iscorrect":true},{"text":"A controller for batch jobs.","iscorrect":false},{"text":"A controller for daemon sets.","iscorrect":false}]},{"questionText":"What is a Deployment in Kubernetes?","type":"","category":"gcp","subcategory":"gke","dateadded":"11-November-2025","certification":"","answerReference":"A controller that manages stateless applications, allowing for declarative updates and rollbacks.","answers":[{"text":"A controller for stateful applications.","iscorrect":false},{"text":"A controller that manages stateless applications, allowing for declarative updates and rollbacks.","iscorrect":true},{"text":"A controller for daemon sets.","iscorrect":false},{"text":"A controller for batch jobs.","iscorrect":false}]},{"questionText":"What is a DaemonSet in Kubernetes?","type":"","category":"gcp","subcategory":"gke","dateadded":"11-November-2025","certification":"","answerReference":"Ensures that a copy of a pod runs on all (or a subset of) nodes in the cluster.","answers":[{"text":"Ensures that a copy of a pod runs on all (or a subset of) nodes in the cluster.","iscorrect":true},{"text":"Ensures that a specified number of pods are running.","iscorrect":false},{"text":"Ensures that pods are scheduled on specific nodes.","iscorrect":false},{"text":"Ensures that stateful applications are managed.","iscorrect":false}]},{"questionText":"What is a Job in Kubernetes?","type":"","category":"gcp","subcategory":"gke","dateadded":"11-November-2025","certification":"","answerReference":"Creates one or more pods and ensures that a specified number of them successfully terminate.","answers":[{"text":"Creates pods that run indefinitely.","iscorrect":false},{"text":"Creates one or more pods and ensures that a specified number of them successfully terminate.","iscorrect":true},{"text":"Creates pods that are distributed across nodes.","iscorrect":false},{"text":"Creates pods that run on all nodes.","iscorrect":false}]},{"questionText":"What are resource requests and limits in Kubernetes?","type":"","category":"gcp","subcategory":"gke","dateadded":"11-November-2025","certification":"","answerReference":"Define the minimum CPU/memory a container needs and the maximum it can consume.","answers":[{"text":"Define the maximum CPU/memory a container can consume.","iscorrect":false},{"text":"Define the minimum CPU/memory a container needs and the maximum it can consume.","iscorrect":true},{"text":"Define the network bandwidth a container can use.","iscorrect":false},{"text":"Define the storage capacity a container can access.","iscorrect":false}]},{"questionText":"What is pod anti-affinity in Kubernetes?","type":"","category":"gcp","subcategory":"gke","dateadded":"11-November-2025","certification":"","answerReference":"A rule that prevents pods from being scheduled on the same node.","answers":[{"text":"A rule that ensures pods are scheduled on the same node.","iscorrect":false},{"text":"A rule that prevents pods from being scheduled on the same node.","iscorrect":true},{"text":"A rule that schedules pods based on their labels.","iscorrect":false},{"text":"A rule that prioritizes pods for scheduling.","iscorrect":false}]},{"questionText":"What is pod affinity in Kubernetes?","type":"","category":"gcp","subcategory":"gke","dateadded":"11-November-2025","certification":"","answerReference":"A rule that encourages pods to be scheduled on the same node or nodes with specific labels.","answers":[{"text":"A rule that prevents pods from being scheduled on the same node.","iscorrect":false},{"text":"A rule that encourages pods to be scheduled on the same node or nodes with specific labels.","iscorrect":true},{"text":"A rule that ensures pods are not scheduled on the same node.","iscorrect":false},{"text":"A rule that schedules pods based on their resource requests.","iscorrect":false}]},{"questionText":"What is a Service in Kubernetes?","type":"","category":"gcp","subcategory":"gke","dateadded":"11-November-2025","certification":"","answerReference":"An abstraction that defines a logical set of pods and a policy by which to access them.","answers":[{"text":"A single pod that provides access to a group of services.","iscorrect":false},{"text":"An abstraction that defines a logical set of pods and a policy by which to access them.","iscorrect":true},{"text":"A network route between pods.","iscorrect":false},{"text":"A load balancer for external traffic.","iscorrect":false}]},{"questionText":"What are the different types of Services in Kubernetes?","type":"","category":"gcp","subcategory":"gke","dateadded":"11-November-2025","certification":"","answerReference":"ClusterIP, NodePort, LoadBalancer, and ExternalName.","answers":[{"text":"Node, Pod, Cluster, and External.","iscorrect":false},{"text":"ClusterIP, NodePort, LoadBalancer, and ExternalName.","iscorrect":true},{"text":"Internal, External, Public, and Private.","iscorrect":false},{"text":"Frontend, Backend, Database, and Cache.","iscorrect":false}]},{"questionText":"What is a PersistentVolume (PV) in Kubernetes?","type":"","category":"gcp","subcategory":"gke","dateadded":"11-November-2025","certification":"","answerReference":"A piece of storage in the cluster that has been provisioned by an administrator or dynamically provisioned using Storage Classes.","answers":[{"text":"A temporary storage volume for pods.","iscorrect":false},{"text":"A piece of storage in the cluster that has been provisioned by an administrator or dynamically provisioned using Storage Classes.","iscorrect":true},{"text":"A network interface for pods.","iscorrect":false},{"text":"A configuration file for pods.","iscorrect":false}]},{"questionText":"What is a PersistentVolumeClaim (PVC) in Kubernetes?","type":"","category":"gcp","subcategory":"gke","dateadded":"11-November-2025","certification":"","answerReference":"A request for storage by a user, which consumes PV resources.","answers":[{"text":"A declaration of storage that is available.","iscorrect":false},{"text":"A request for storage by a user, which consumes PV resources.","iscorrect":true},{"text":"A dynamic provisioner for storage.","iscorrect":false},{"text":"A way to mount local storage to pods.","iscorrect":false}]},{"questionText":"What is a StorageClass in Kubernetes?","type":"","category":"gcp","subcategory":"gke","dateadded":"11-November-2025","certification":"","answerReference":"Provides a way for administrators to describe the 'classes' of storage they offer.","answers":[{"text":"A specific type of persistent volume.","iscorrect":false},{"text":"Provides a way for administrators to describe the 'classes' of storage they offer.","iscorrect":true},{"text":"A mount point for network storage.","iscorrect":false},{"text":"A template for creating persistent volume claims.","iscorrect":false}]},{"questionText":"What is a ReplicaSet in Kubernetes?","type":"","category":"gcp","subcategory":"gke","dateadded":"11-November-2025","certification":"","answerReference":"Ensures that a specified number of pod replicas are running at any given time.","answers":[{"text":"Ensures that pods are always scheduled on the same node.","iscorrect":false},{"text":"Ensures that a specified number of pod replicas are running at any given time.","iscorrect":true},{"text":"Ensures that stateful applications have stable identities.","iscorrect":false},{"text":"Ensures that pods are created only once.","iscorrect":false}]},{"questionText":"What is a Rolling Update strategy in Deployments?","type":"","category":"gcp","subcategory":"gke","dateadded":"11-November-2025","certification":"","answerReference":"Gradually replaces old pods with new ones, ensuring zero downtime.","answers":[{"text":"Replaces all old pods with new ones simultaneously.","iscorrect":false},{"text":"Gradually replaces old pods with new ones, ensuring zero downtime.","iscorrect":true},{"text":"Rolls back to the previous version of the application.","iscorrect":false},{"text":"Keeps both old and new pods running indefinitely.","iscorrect":false}]},{"questionText":"What is a Blue/Green Deployment strategy?","type":"","category":"gcp","subcategory":"gke","dateadded":"11-November-2025","certification":"","answerReference":"Runs two identical production environments, 'Blue' (current) and 'Green' (new), and switches traffic to Green.","answers":[{"text":"Runs the new version alongside the old and gradually phases out the old.","iscorrect":false},{"text":"Runs two identical production environments, 'Blue' (current) and 'Green' (new), and switches traffic to Green.","iscorrect":true},{"text":"Deploys the new version only after the old version is completely removed.","iscorrect":false},{"text":"Deploys the new version to a small subset of users first.","iscorrect":false}]},{"questionText":"What is a Canary Deployment strategy?","type":"","category":"gcp","subcategory":"gke","dateadded":"11-November-2025","certification":"","answerReference":"Rolls out new versions to a small subset of users first, then gradually increases the rollout if successful.","answers":[{"text":"Runs two identical production environments and switches traffic.","iscorrect":false},{"text":"Deploys the new version to a small subset of users first, then gradually increases the rollout if successful.","iscorrect":true},{"text":"Gradually replaces old pods with new ones without user interruption.","iscorrect":false},{"text":"Deploys the new version to all users at once.","iscorrect":false}]},{"questionText":"What is a namespace in Kubernetes?","type":"","category":"gcp","subcategory":"gke","dateadded":"11-November-2025","certification":"","answerReference":"A way to divide cluster resources between multiple users or teams.","answers":[{"text":"A way to define network policies.","iscorrect":false},{"text":"A way to divide cluster resources between multiple users or teams.","iscorrect":true},{"text":"A persistent storage volume.","iscorrect":false},{"text":"A type of Kubernetes node.","iscorrect":false}]},{"questionText":"What is a taint and toleration in Kubernetes?","type":"","category":"gcp","subcategory":"gke","dateadded":"11-November-2025","certification":"","answerReference":"Taints on nodes repel pods, and tolerations on pods allow them to be scheduled on tainted nodes.","answers":[{"text":"Taints on nodes attract pods, and tolerations repel them.","iscorrect":false},{"text":"Taints on nodes repel pods, and tolerations on pods allow them to be scheduled on tainted nodes.","iscorrect":true},{"text":"Taints define resource limits, and tolerations define resource requests.","iscorrect":false},{"text":"Taints are used for network isolation, and tolerations for service discovery.","iscorrect":false}]},{"questionText":"What is node taints?","type":"","category":"gcp","subcategory":"gke","dateadded":"11-November-2025","certification":"","answerReference":"Marks nodes to repel pods that do not tolerate them.","answers":[{"text":"Marks nodes to attract specific pods.","iscorrect":false},{"text":"Marks nodes to repel pods that do not tolerate them.","iscorrect":true},{"text":"Marks nodes to limit resource usage.","iscorrect":false},{"text":"Marks nodes for special network configurations.","iscorrect":false}]},{"questionText":"What are pod tolerations?","type":"","category":"gcp","subcategory":"gke","dateadded":"11-November-2025","certification":"","answerReference":"Allow pods to be scheduled on nodes with matching taints.","answers":[{"text":"Prevent pods from being scheduled on specific nodes.","iscorrect":false},{"text":"Allow pods to be scheduled on nodes with matching taints.","iscorrect":true},{"text":"Specify the number of replicas for a pod.","iscorrect":false},{"text":"Define resource requests for a pod.","iscorrect":false}]},{"questionText":"What is autoscaling in the context of GKE?","type":"","category":"gcp","subcategory":"gke","dateadded":"11-November-2025","certification":"","answerReference":"Automatically adjusting resources (nodes or pods) based on demand.","answers":[{"text":"Manually adjusting resources when needed.","iscorrect":false},{"text":"Automatically adjusting resources (nodes or pods) based on demand.","iscorrect":true},{"text":"Setting fixed resource limits for all applications.","iscorrect":false},{"text":"Scaling down resources only when explicitly instructed.","iscorrect":false}]},{"questionText":"What is the difference between Cluster Autoscaler and Horizontal Pod Autoscaler?","type":"","category":"gcp","subcategory":"gke","dateadded":"11-November-2025","certification":"","answerReference":"Cluster Autoscaler scales nodes, while HPA scales pods.","answers":[{"text":"HPA scales nodes, and Cluster Autoscaler scales pods.","iscorrect":false},{"text":"Cluster Autoscaler scales nodes, while HPA scales pods.","iscorrect":true},{"text":"Both scale nodes.","iscorrect":false},{"text":"Both scale pods.","iscorrect":false}]},{"questionText":"What is the purpose of resource quotas in Kubernetes?","type":"","category":"gcp","subcategory":"gke","dateadded":"11-November-2025","certification":"","answerReference":"To limit the aggregate resource consumption per namespace.","answers":[{"text":"To limit resource consumption per pod.","iscorrect":false},{"text":"To limit the aggregate resource consumption per namespace.","iscorrect":true},{"text":"To define resource requests for nodes.","iscorrect":false},{"text":"To set network bandwidth limits.","iscorrect":false}]},{"questionText":"What is a LimitRange in Kubernetes?","type":"","category":"gcp","subcategory":"gke","dateadded":"11-November-2025","certification":"","answerReference":"Enforces constraints on resource allocation for individual pods and containers within a namespace.","answers":[{"text":"Enforces constraints on resource allocation for individual pods and containers within a namespace.","iscorrect":true},{"text":"Limits the total resources available in a namespace.","iscorrect":false},{"text":"Defines the number of nodes in a cluster.","iscorrect":false},{"text":"Sets default resource requests for all pods.","iscorrect":false}]},{"questionText":"What is the default CPU and memory request for a container if not specified?","type":"","category":"gcp","subcategory":"gke","dateadded":"11-November-2025","certification":"","answerReference":"There is no default; it's best practice to always specify requests.","answers":[{"text":"1 CPU and 1 GiB of memory.","iscorrect":false},{"text":"Kubernetes assigns a small default based on node capacity.","iscorrect":false},{"text":"There is no default; it's best practice to always specify requests.","iscorrect":true},{"text":"0 CPU and 0 memory, allowing unlimited usage.","iscorrect":false}]},{"questionText":"How does GKE handle node scaling when using Cluster Autoscaler?","type":"","category":"gcp","subcategory":"gke","dateadded":"11-November-2025","certification":"","answerReference":"It adds or removes nodes to node pools based on pending pods that cannot be scheduled and nodes that are underutilized.","answers":[{"text":"It only adds nodes, never removes them.","iscorrect":false},{"text":"It adds or removes nodes to node pools based on pending pods that cannot be scheduled and nodes that are underutilized.","iscorrect":true},{"text":"It manually prompts the user to add or remove nodes.","iscorrect":false},{"text":"It scales pods, not nodes.","iscorrect":false}]},{"questionText":"What is the `requests.cpu` field in a pod specification used for?","type":"","category":"gcp","subcategory":"gke","dateadded":"11-November-2025","certification":"","answerReference":"To inform the Kubernetes scheduler about the minimum CPU a container needs to run.","answers":[{"text":"To set the maximum CPU a container can use.","iscorrect":false},{"text":"To inform the Kubernetes scheduler about the minimum CPU a container needs to run.","iscorrect":true},{"text":"To set the CPU throttling for a container.","iscorrect":false},{"text":"To define the CPU usage for billing.","iscorrect":false}]},{"questionText":"What is the `limits.cpu` field in a pod specification used for?","type":"","category":"gcp","subcategory":"gke","dateadded":"11-November-2025","certification":"","answerReference":"To set the maximum CPU a container is allowed to consume.","answers":[{"text":"To set the minimum CPU a container needs.","iscorrect":false},{"text":"To set the maximum CPU a container is allowed to consume.","iscorrect":true},{"text":"To guarantee CPU availability.","iscorrect":false},{"text":"To control CPU share allocation.","iscorrect":false}]},{"questionText":"What is the `requests.memory` field in a pod specification used for?","type":"","category":"gcp","subcategory":"gke","dateadded":"11-November-2025","certification":"","answerReference":"To inform the Kubernetes scheduler about the minimum memory a container needs to run.","answers":[{"text":"To set the maximum memory a container can use.","iscorrect":false},{"text":"To inform the Kubernetes scheduler about the minimum memory a container needs to run.","iscorrect":true},{"text":"To set the memory swap usage for a container.","iscorrect":false},{"text":"To define the memory usage for billing.","iscorrect":false}]},{"questionText":"What is the `limits.memory` field in a pod specification used for?","type":"","category":"gcp","subcategory":"gke","dateadded":"11-November-2025","certification":"","answerReference":"To set the maximum memory a container is allowed to consume.","answers":[{"text":"To set the minimum memory a container needs.","iscorrect":false},{"text":"To set the maximum memory a container is allowed to consume.","iscorrect":true},{"text":"To guarantee memory availability.","iscorrect":false},{"text":"To control memory swap allocation.","iscorrect":false}]},{"questionText":"What happens if a pod exceeds its memory limit?","type":"","category":"gcp","subcategory":"gke","dateadded":"11-November-2025","certification":"","answerReference":"The container running the pod will be terminated (OOMKilled).","answers":[{"text":"The pod will be throttled and slowed down.","iscorrect":false},{"text":"The container running the pod will be terminated (OOMKilled).","iscorrect":true},{"text":"The node will be restarted.","iscorrect":false},{"text":"Kubernetes will automatically increase the memory limit.","iscorrect":false}]},{"questionText":"What happens if a pod exceeds its CPU limit?","type":"","category":"gcp","subcategory":"gke","dateadded":"11-November-2025","certification":"","answerReference":"The container will be throttled, meaning its CPU usage will be restricted.","answers":[{"text":"The container will be terminated.","iscorrect":false},{"text":"The container will be throttled, meaning its CPU usage will be restricted.","iscorrect":true},{"text":"The pod will be evicted from the node.","iscorrect":false},{"text":"Kubernetes will automatically increase the CPU limit.","iscorrect":false}]},{"questionText":"What is the role of the GKE control plane in scaling?","type":"","category":"gcp","subcategory":"gke","dateadded":"11-November-2025","certification":"","answerReference":"It manages the cluster state, schedules pods, and interacts with Cluster Autoscaler and HPA.","answers":[{"text":"It directly manages the CPU and memory of individual pods.","iscorrect":false},{"text":"It manages the cluster state, schedules pods, and interacts with Cluster Autoscaler and HPA.","iscorrect":true},{"text":"It only handles networking for the cluster.","iscorrect":false},{"text":"It is responsible for user authentication and authorization only.","iscorrect":false}]},{"questionText":"What metric does the Horizontal Pod Autoscaler typically use to scale pods?","type":"","category":"gcp","subcategory":"gke","dateadded":"11-November-2025","certification":"","answerReference":"CPU utilization or memory utilization of the pods.","answers":[{"text":"The number of nodes in the cluster.","iscorrect":false},{"text":"CPU utilization or memory utilization of the pods.","iscorrect":true},{"text":"The total storage capacity of the cluster.","iscorrect":false},{"text":"The latency of requests to the pods.","iscorrect":false}]},{"questionText":"What is the `targetAverageUtilization` field in an HPA?","type":"","category":"gcp","subcategory":"gke","dateadded":"11-November-2025","certification":"","answerReference":"The desired average resource utilization across all pods managed by the HPA.","answers":[{"text":"The maximum allowed resource utilization.","iscorrect":false},{"text":"The desired average resource utilization across all pods managed by the HPA.","iscorrect":true},{"text":"The minimum required resource utilization.","iscorrect":false},{"text":"The current average resource utilization.","iscorrect":false}]},{"questionText":"What is the `targetAverageValue` field in an HPA?","type":"","category":"gcp","subcategory":"gke","dateadded":"11-November-2025","certification":"","answerReference":"The desired average value of a custom metric across all pods.","answers":[{"text":"The minimum allowed value of a custom metric.","iscorrect":false},{"text":"The desired average value of a custom metric across all pods.","iscorrect":true},{"text":"The maximum allowed value of a custom metric.","iscorrect":false},{"text":"The current average value of a custom metric.","iscorrect":false}]},{"questionText":"What is a custom metric for HPA?","type":"","category":"gcp","subcategory":"gke","dateadded":"11-November-2025","certification":"","answerReference":"A metric not built into Kubernetes, like requests per second or queue depth, exposed via a custom metrics API.","answers":[{"text":"CPU and memory utilization.","iscorrect":false},{"text":"A metric not built into Kubernetes, like requests per second or queue depth, exposed via a custom metrics API.","iscorrect":true},{"text":"The number of running pods.","iscorrect":false},{"text":"The available disk space on nodes.","iscorrect":false}]},{"questionText":"What is a metric server in Kubernetes?","type":"","category":"gcp","subcategory":"gke","dateadded":"11-November-2025","certification":"","answerReference":"Provides resource usage data (CPU/memory) for pods and nodes, used by HPA and VPA.","answers":[{"text":"Manages the lifecycle of pods.","iscorrect":false},{"text":"Provides resource usage data (CPU/memory) for pods and nodes, used by HPA and VPA.","iscorrect":true},{"text":"Handles network traffic routing.","iscorrect":false},{"text":"Stores persistent data for applications.","iscorrect":false}]},{"questionText":"What is `kube-state-metrics`?","type":"","category":"gcp","subcategory":"gke","dateadded":"11-November-2025","certification":"","answerReference":"A service that generates metrics about the state of Kubernetes objects.","answers":[{"text":"A service that collects logs from pods.","iscorrect":false},{"text":"A service that generates metrics about the state of Kubernetes objects.","iscorrect":true},{"text":"A service that monitors network traffic.","iscorrect":false},{"text":"A service that manages persistent volumes.","iscorrect":false}]},{"questionText":"What is the recommended way to achieve high availability for GKE applications?","type":"","category":"gcp","subcategory":"gke","dateadded":"11-November-2025","certification":"","answerReference":"Deploying applications across multiple zones within a region and using multiple replicas.","answers":[{"text":"Deploying all replicas on a single node.","iscorrect":false},{"text":"Deploying applications across multiple zones within a region and using multiple replicas.","iscorrect":true},{"text":"Running a single replica and hoping for the best.","iscorrect":false},{"text":"Deploying applications across multiple regions.","iscorrect":false}]},{"questionText":"What is PodDisruptionBudget (PDB)?","type":"","category":"gcp","subcategory":"gke","dateadded":"11-November-2025","certification":"","answerReference":"Ensures a minimum number of pods are available during voluntary disruptions (e.g., node upgrades).","answers":[{"text":"Ensures a maximum number of pods are running.","iscorrect":false},{"text":"Ensures a minimum number of pods are available during voluntary disruptions (e.g., node upgrades).","iscorrect":true},{"text":"Defines the maximum number of pods that can be scheduled.","iscorrect":false},{"text":"Guarantees that pods are not evicted during voluntary disruptions.","iscorrect":false}]},{"questionText":"How does GKE handle upgrades of nodes in a node pool?","type":"","category":"gcp","subcategory":"gke","dateadded":"11-November-2025","certification":"","answerReference":"It performs rolling upgrades, replacing nodes one by one to minimize disruption.","answers":[{"text":"It upgrades all nodes simultaneously.","iscorrect":false},{"text":"It performs rolling upgrades, replacing nodes one by one to minimize disruption.","iscorrect":true},{"text":"It requires manual node replacement.","iscorrect":false},{"text":"It deletes and recreates the entire node pool.","iscorrect":false}]},{"questionText":"What is a pre-emptible VM in GKE?","type":"","category":"gcp","subcategory":"gke","dateadded":"11-November-2025","certification":"","answerReference":"VMs that are subject to termination by Google Cloud for cost savings, suitable for fault-tolerant workloads.","answers":[{"text":"VMs that are guaranteed to run without interruption.","iscorrect":false},{"text":"VMs that are subject to termination by Google Cloud for cost savings, suitable for fault-tolerant workloads.","iscorrect":true},{"text":"VMs that are used for the GKE control plane.","iscorrect":false},{"text":"VMs that have enhanced security features.","iscorrect":false}]},{"questionText":"How can you scale GKE node pools based on custom metrics?","type":"","category":"gcp","subcategory":"gke","dateadded":"11-November-2025","certification":"","answerReference":"By configuring HPA to use custom metrics provided by Prometheus or other monitoring solutions.","answers":[{"text":"HPA only supports CPU and memory.","iscorrect":false},{"text":"By configuring HPA to use custom metrics provided by Prometheus or other monitoring solutions.","iscorrect":true},{"text":"Node pools cannot be scaled based on custom metrics.","iscorrect":false},{"text":"You need to manually reconfigure the node pool.","iscorrect":false}]},{"questionText":"What is the `maxSurge` parameter in a Deployment's rolling update strategy?","type":"","category":"gcp","subcategory":"gke","dateadded":"11-November-2025","certification":"","answerReference":"Specifies the maximum number of pods that can be created above the desired number of replicas during an update.","answers":[{"text":"The maximum number of pods that can be unavailable during an update.","iscorrect":false},{"text":"Specifies the maximum number of pods that can be created above the desired number of replicas during an update.","iscorrect":true},{"text":"The minimum number of old pods to keep running.","iscorrect":false},{"text":"The maximum number of old pods to terminate at once.","iscorrect":false}]},{"questionText":"What is the `maxUnavailable` parameter in a Deployment's rolling update strategy?","type":"","category":"gcp","subcategory":"gke","dateadded":"11-November-2025","certification":"","answerReference":"Specifies the maximum number of pods that can be unavailable during an update.","answers":[{"text":"Specifies the maximum number of pods that can be unavailable during an update.","iscorrect":true},{"text":"Specifies the maximum number of pods that can be created above the desired number of replicas.","iscorrect":false},{"text":"The minimum number of new pods to be created.","iscorrect":false},{"text":"The maximum number of new pods to be created.","iscorrect":false}]},{"questionText":"What is the purpose of a PriorityClass in Kubernetes?","type":"","category":"gcp","subcategory":"gke","dateadded":"11-November-2025","certification":"","answerReference":"Allows you to control the relative priority of pods, influencing scheduling decisions.","answers":[{"text":"Defines resource limits for pods.","iscorrect":false},{"text":"Allows you to control the relative priority of pods, influencing scheduling decisions.","iscorrect":true},{"text":"Specifies network policies for pods.","iscorrect":false},{"text":"Determines the storage class for volumes.","iscorrect":false}]},{"questionText":"What are the implications of setting resource `limits` higher than `requests` for a container?","type":"","category":"gcp","subcategory":"gke","dateadded":"11-November-2025","certification":"","answerReference":"The container can burst above its request up to its limit, but may be throttled if it consistently exceeds its request.","answers":[{"text":"The container will be terminated if it exceeds its request.","iscorrect":false},{"text":"The container can burst above its request up to its limit, but may be throttled if it consistently exceeds its request.","iscorrect":true},{"text":"The container will be guaranteed to have resources up to its limit.","iscorrect":false},{"text":"It has no practical effect on resource allocation.","iscorrect":false}]},{"questionText":"What is the benefit of using node pools with different machine types in GKE?","type":"","category":"gcp","subcategory":"gke","dateadded":"11-November-2025","certification":"","answerReference":"Allows for optimization of cost and performance by using specialized machines for different workloads.","answers":[{"text":"It increases the complexity of node management.","iscorrect":false},{"text":"Allows for optimization of cost and performance by using specialized machines for different workloads.","iscorrect":true},{"text":"It does not provide any significant benefits.","iscorrect":false},{"text":"It forces all pods to run on nodes with the same machine type.","iscorrect":false}]},{"questionText":"What is node auto-provisioning in GKE?","type":"","category":"gcp","subcategory":"gke","dateadded":"11-November-2025","certification":"","answerReference":"Automatically creates new node pools based on pending pods that cannot be scheduled on existing nodes.","answers":[{"text":"Automatically scales the number of pods in existing node pools.","iscorrect":false},{"text":"Automatically creates new node pools based on pending pods that cannot be scheduled on existing nodes.","iscorrect":true},{"text":"Manually configures node pools based on user input.","iscorrect":false},{"text":"Automatically removes underutilized nodes from existing node pools.","iscorrect":false}]},{"questionText":"What is the difference between scaling `nodes` and scaling `pods`?","type":"","category":"gcp","subcategory":"gke","dateadded":"11-November-2025","certification":"","answerReference":"Scaling nodes increases the compute capacity of the cluster, while scaling pods increases the number of application instances.","answers":[{"text":"Scaling pods increases compute capacity, scaling nodes increases application instances.","iscorrect":false},{"text":"Scaling nodes increases the compute capacity of the cluster, while scaling pods increases the number of application instances.","iscorrect":true},{"text":"They are the same thing and can be used interchangeably.","iscorrect":false},{"text":"Scaling nodes affects only system pods, while scaling pods affects user applications.","iscorrect":false}]},{"questionText":"What are the considerations for setting `maxReplicas` in a Horizontal Pod Autoscaler?","type":"","category":"gcp","subcategory":"gke","dateadded":"11-November-2025","certification":"","answerReference":"Should be set to accommodate peak load without exceeding resource availability or incurring excessive costs.","answers":[{"text":"Should be set to the minimum number of pods required.","iscorrect":false},{"text":"Should be set to accommodate peak load without exceeding resource availability or incurring excessive costs.","iscorrect":true},{"text":"Should be set to a fixed number, regardless of load.","iscorrect":false},{"text":"Should be set to a very high number to ensure scalability.","iscorrect":false}]},{"questionText":"What is the role of `kube-scheduler` in scaling?","type":"","category":"gcp","subcategory":"gke","dateadded":"11-November-2025","certification":"","answerReference":"It decides which node a pod should run on based on resource requests, affinity rules, and node taints/tolerations.","answers":[{"text":"It decides how many replicas a deployment should have.","iscorrect":false},{"text":"It decides which node a pod should run on based on resource requests, affinity rules, and node taints/tolerations.","iscorrect":true},{"text":"It scales the number of nodes in the cluster.","iscorrect":false},{"text":"It monitors the health of running pods.","iscorrect":false}]},{"questionText":"What is the impact of using `nodeSelector` on scaling?","type":"","category":"gcp","subcategory":"gke","dateadded":"11-November-2025","certification":"","answerReference":"It restricts pods to specific nodes, which can hinder autoscaling if not managed carefully.","answers":[{"text":"It automatically scales the node pool to accommodate restricted pods.","iscorrect":false},{"text":"It restricts pods to specific nodes, which can hinder autoscaling if not managed carefully.","iscorrect":true},{"text":"It ensures pods are evenly distributed across all nodes.","iscorrect":false},{"text":"It has no impact on scaling.","iscorrect":false}]},{"questionText":"What is the purpose of GKE's Autopilot mode in relation to scaling?","type":"","category":"gcp","subcategory":"gke","dateadded":"11-November-2025","certification":"","answerReference":"Abstracts away cluster management and node scaling, automatically scaling nodes and pods based on workload.","answers":[{"text":"Provides more granular control over node scaling.","iscorrect":false},{"text":"Abstracts away cluster management and node scaling, automatically scaling nodes and pods based on workload.","iscorrect":true},{"text":"Requires manual configuration of all autoscaling parameters.","iscorrect":false},{"text":"Focuses solely on pod scaling, not node scaling.","iscorrect":false}]},{"questionText":"What is the `coolDownPeriod` in Cluster Autoscaler?","type":"","category":"gcp","subcategory":"gke","dateadded":"11-November-2025","certification":"","answerReference":"The time after a node is added before it can be scaled down, to allow pods to settle.","answers":[{"text":"The time after a node is removed before a new one can be added.","iscorrect":false},{"text":"The time after a node is added before it can be scaled down, to allow pods to settle.","iscorrect":true},{"text":"The maximum duration a node can be scaled up.","iscorrect":false},{"text":"The minimum duration a node must remain provisioned.","iscorrect":false}]},{"questionText":"What is the difference between `HorizontalPodAutoscaler` and `VerticalPodAutoscaler` in terms of what they scale?","type":"","category":"gcp","subcategory":"gke","dateadded":"11-November-2025","certification":"","answerReference":"HPA scales the number of pod replicas, while VPA scales the resource requests/limits of existing pods.","answers":[{"text":"HPA scales resource requests/limits, VPA scales the number of replicas.","iscorrect":false},{"text":"HPA scales the number of pod replicas, while VPA scales the resource requests/limits of existing pods.","iscorrect":true},{"text":"Both scale the number of pod replicas.","iscorrect":false},{"text":"Both scale the resource requests/limits of existing pods.","iscorrect":false}]},{"questionText":"How does VPA typically update pod resource requests?","type":"","category":"gcp","subcategory":"gke","dateadded":"11-November-2025","certification":"","answerReference":"It can recommend updates, or it can automatically recreate pods with updated resource requests.","answers":[{"text":"It directly modifies the running containers' resource allocations.","iscorrect":false},{"text":"It can recommend updates, or it can automatically recreate pods with updated resource requests.","iscorrect":true},{"text":"It only provides metrics for manual adjustment.","iscorrect":false},{"text":"It increases resource requests but never decreases them.","iscorrect":false}]},{"questionText":"What is the `podAntiAffinity` `requiredDuringSchedulingIgnoredDuringExecution` rule?","type":"","category":"gcp","subcategory":"gke","dateadded":"11-November-2025","certification":"","answerReference":"Ensures pods are not scheduled on the same node, but if they end up there due to node failure, they are not evicted.","answers":[{"text":"Ensures pods are scheduled on the same node.","iscorrect":false},{"text":"Ensures pods are not scheduled on the same node, but if they end up there due to node failure, they are not evicted.","iscorrect":true},{"text":"Ensures pods are evicted if they end up on the same node.","iscorrect":false},{"text":"Only considers scheduling, ignores execution state.","iscorrect":false}]},{"questionText":"What is the `podAffinity` `preferredDuringSchedulingIgnoredDuringExecution` rule?","type":"","category":"gcp","subcategory":"gke","dateadded":"11-November-2025","certification":"","answerReference":"Attempts to schedule pods on nodes with matching labels but does not guarantee it and doesn't evict if the condition is lost.","answers":[{"text":"Guarantees pods are scheduled on nodes with matching labels.","iscorrect":false},{"text":"Attempts to schedule pods on nodes with matching labels but does not guarantee it and doesn't evict if the condition is lost.","iscorrect":true},{"text":"Prevents pods from being scheduled on nodes with matching labels.","iscorrect":false},{"text":"Only considers execution, ignores scheduling.","iscorrect":false}]},{"questionText":"What are the potential issues with aggressive autoscaling?","type":"","category":"gcp","subcategory":"gke","dateadded":"11-November-2025","certification":"","answerReference":"Can lead to excessive costs, frequent node churn, and potential instability if scaling up/down too rapidly.","answers":[{"text":"Always results in improved performance and lower costs.","iscorrect":false},{"text":"Can lead to excessive costs, frequent node churn, and potential instability if scaling up/down too rapidly.","iscorrect":true},{"text":"Typically has no negative side effects.","iscorrect":false},{"text":"Only affects the control plane, not the workloads.","iscorrect":false}]},{"questionText":"What is the purpose of `topologySpreadConstraints` in Kubernetes?","type":"","category":"gcp","subcategory":"gke","dateadded":"11-November-2025","certification":"","answerReference":"Ensures that pods are spread out across nodes, availability zones, or regions for better availability and resource utilization.","answers":[{"text":"Ensures that pods are scheduled on the same node for better performance.","iscorrect":false},{"text":"Ensures that pods are spread out across nodes, availability zones, or regions for better availability and resource utilization.","iscorrect":true},{"text":"Limits the number of pods that can be scheduled.","iscorrect":false},{"text":"Assigns specific roles to pods.","iscorrect":false}]},{"questionText":"How can GKE scaling be monitored?","type":"","category":"gcp","subcategory":"gke","dateadded":"11-November-2025","certification":"","answerReference":"Using Google Cloud Monitoring (formerly Stackdriver) to track cluster and pod metrics, and autoscaler events.","answers":[{"text":"Only by manually checking node counts.","iscorrect":false},{"text":"Using Google Cloud Monitoring (formerly Stackdriver) to track cluster and pod metrics, and autoscaler events.","iscorrect":true},{"text":"By examining Kubernetes event logs only.","iscorrect":false},{"text":"Scaling metrics are not directly visible in GKE.","iscorrect":false}]},{"questionText":"What is the difference between `minReplicas` and `maxReplicas` in HPA?","type":"","category":"gcp","subcategory":"gke","dateadded":"11-November-2025","certification":"","answerReference":"`minReplicas` is the target number of pods when under low load, and `maxReplicas` is the target when under high load.","answers":[{"text":"`minReplicas` is the target when under high load, and `maxReplicas` when under low load.","iscorrect":false},{"text":"`minReplicas` is the target number of pods when under low load, and `maxReplicas` is the target when under high load.","iscorrect":true},{"text":"`minReplicas` dictates the node pool size, `maxReplicas` dictates pod count.","iscorrect":false},{"text":"They are the same and represent the desired number of pods.","iscorrect":false}]},{"questionText":"What is the significance of `stabilizationWindowSeconds` in HPA?","type":"","category":"gcp","subcategory":"gke","dateadded":"11-November-2025","certification":"","answerReference":"A period after a scaling event during which further scaling actions are suppressed to prevent thrashing.","answers":[{"text":"The time it takes for a new pod to start.","iscorrect":false},{"text":"A period after a scaling event during which further scaling actions are suppressed to prevent thrashing.","iscorrect":true},{"text":"The minimum time between scaling events.","iscorrect":false},{"text":"The duration for which metrics are collected.","iscorrect":false}]},{"questionText":"What happens to pods when a node is scaled down by Cluster Autoscaler?","type":"","category":"gcp","subcategory":"gke","dateadded":"11-November-2025","certification":"","answerReference":"Pods are evicted from the node, and Kubernetes attempts to reschedule them on other available nodes.","answers":[{"text":"Pods are deleted along with the node.","iscorrect":false},{"text":"Pods are evicted from the node, and Kubernetes attempts to reschedule them on other available nodes.","iscorrect":true},{"text":"Pods are migrated to a new node automatically.","iscorrect":false},{"text":"The node remains with the pods until manually terminated.","iscorrect":false}]},{"questionText":"What is a `HorizontalPodAutoscaler` behavior configuration?","type":"","category":"gcp","subcategory":"gke","dateadded":"11-November-2025","certification":"","answerReference":"Allows fine-tuning of scaling behavior, such as scaling up/down stabilization windows per metric.","answers":[{"text":"Defines the maximum number of pods per node.","iscorrect":false},{"text":"Allows fine-tuning of scaling behavior, such as scaling up/down stabilization windows per metric.","iscorrect":true},{"text":"Specifies the machine types for node pools.","iscorrect":false},{"text":"Configures the default resource requests for pods.","iscorrect":false}]},{"questionText":"What is the purpose of `podDisruptionBudget`'s `minAvailable` field?","type":"","category":"gcp","subcategory":"gke","dateadded":"11-November-2025","certification":"","answerReference":"Specifies the minimum number of pods that must remain available during voluntary disruptions.","answers":[{"text":"Specifies the maximum number of pods that can be unavailable.","iscorrect":false},{"text":"Specifies the minimum number of pods that must remain available during voluntary disruptions.","iscorrect":true},{"text":"Specifies the minimum number of replicas to maintain.","iscorrect":false},{"text":"Specifies the minimum number of nodes that must be available.","iscorrect":false}]},{"questionText":"What is the `maxPodsPerNode` setting in GKE node pools?","type":"","category":"gcp","subcategory":"gke","dateadded":"11-November-2025","certification":"","answerReference":"A limit on the number of pods that can be scheduled on a single node, considering its resources.","answers":[{"text":"A hard limit on the number of nodes in the pool.","iscorrect":false},{"text":"A limit on the number of pods that can be scheduled on a single node, considering its resources.","iscorrect":true},{"text":"A minimum number of pods required per node.","iscorrect":false},{"text":"A setting for network traffic distribution.","iscorrect":false}]},{"questionText":"What is the role of `PodPriority` when combined with autoscaling?","type":"","category":"gcp","subcategory":"gke","dateadded":"11-November-2025","certification":"","answerReference":"Ensures that critical pods are scheduled and maintained, even when the cluster is under pressure or scaling down.","answers":[{"text":"It prevents pods from being scaled down.","iscorrect":false},{"text":"Ensures that critical pods are scheduled and maintained, even when the cluster is under pressure or scaling down.","iscorrect":true},{"text":"It dictates the scaling limits for pods.","iscorrect":false},{"text":"It has no interaction with autoscaling.","iscorrect":false}]},{"questionText":"What is the `scaleDown` policy in Cluster Autoscaler?","type":"","category":"gcp","subcategory":"gke","dateadded":"11-November-2025","certification":"","answerReference":"Determines how and when the Cluster Autoscaler removes underutilized nodes.","answers":[{"text":"Determines how and when the Cluster Autoscaler adds new nodes.","iscorrect":false},{"text":"Determines how and when the Cluster Autoscaler removes underutilized nodes.","iscorrect":true},{"text":"Determines the minimum number of nodes in a node pool.","iscorrect":false},{"text":"Determines the maximum number of pods per node.","iscorrect":false}]},{"questionText":"What is the `scaleUp` policy in Cluster Autoscaler?","type":"","category":"gcp","subcategory":"gke","dateadded":"11-November-2025","certification":"","answerReference":"Determines how and when the Cluster Autoscaler adds new nodes to the cluster.","answers":[{"text":"Determines how and when the Cluster Autoscaler removes underutilized nodes.","iscorrect":false},{"text":"Determines how and when the Cluster Autoscaler adds new nodes to the cluster.","iscorrect":true},{"text":"Determines the minimum number of pods per node.","iscorrect":false},{"text":"Determines the maximum number of pods per node.","iscorrect":false}]},{"questionText":"What is the role of `PodAffinityTerm` and `PodAntiAffinityTerm` in scaling?","type":"","category":"gcp","subcategory":"gke","dateadded":"11-November-2025","certification":"","answerReference":"They influence scheduling decisions, which can indirectly affect autoscaling by controlling where pods can land and thus whether new nodes are needed.","answers":[{"text":"They directly trigger scaling of nodes or pods.","iscorrect":false},{"text":"They influence scheduling decisions, which can indirectly affect autoscaling by controlling where pods can land and thus whether new nodes are needed.","iscorrect":true},{"text":"They only affect stateless applications.","iscorrect":false},{"text":"They are used for defining network policies.","iscorrect":false}]},{"questionText":"What is the `nodeTolerations` parameter in a GKE node pool configuration?","type":"","category":"gcp","subcategory":"gke","dateadded":"11-November-2025","certification":"","answerReference":"Allows nodes in the pool to accept pods that have matching tolerations, potentially impacting scheduling and autoscaling.","answers":[{"text":"Defines the maximum number of pods that can run on the nodes.","iscorrect":false},{"text":"Allows nodes in the pool to accept pods that have matching tolerations, potentially impacting scheduling and autoscaling.","iscorrect":true},{"text":"Specifies the machine types for the nodes.","iscorrect":false},{"text":"Configures network settings for the nodes.","iscorrect":false}]},{"questionText":"How does GKE's regional cluster architecture affect scaling?","type":"","category":"gcp","subcategory":"gke","dateadded":"11-November-2025","certification":"","answerReference":"It provides higher availability for the control plane and allows for distributing node pools across multiple zones for application resilience.","answers":[{"text":"It limits scaling capabilities to a single zone.","iscorrect":false},{"text":"It provides higher availability for the control plane and allows for distributing node pools across multiple zones for application resilience.","iscorrect":true},{"text":"It requires manual scaling of each zone independently.","iscorrect":false},{"text":"It has no impact on scaling strategies.","iscorrect":false}]},{"questionText":"What is the `NodeAutoprovisioning` `maxSurge` configuration?","type":"","category":"gcp","subcategory":"gke","dateadded":"11-November-2025","certification":"","answerReference":"Specifies the maximum number of nodes that can be added to a node pool during auto-provisioning.","answers":[{"text":"Specifies the maximum number of pods that can be created.","iscorrect":false},{"text":"Specifies the maximum number of nodes that can be added to a node pool during auto-provisioning.","iscorrect":true},{"text":"Specifies the maximum number of nodes that can be removed.","iscorrect":false},{"text":"Specifies the minimum number of nodes that must be present.","iscorrect":false}]},{"questionText":"What is the `NodeAutoprovisioning` `maxTotalInstances` configuration?","type":"","category":"gcp","subcategory":"gke","dateadded":"11-November-2025","certification":"","answerReference":"Sets an upper limit on the total number of nodes across all node pools created by node auto-provisioning.","answers":[{"text":"Sets an upper limit on the number of pods per node.","iscorrect":false},{"text":"Sets an upper limit on the total number of nodes across all node pools created by node auto-provisioning.","iscorrect":true},{"text":"Sets an upper limit on the number of CPU cores in the cluster.","iscorrect":false},{"text":"Sets an upper limit on the total memory in the cluster.","iscorrect":false}]},{"questionText":"What is the `NodeAutoprovisioning` `maxScaleDownDeltaInstanceCount` configuration?","type":"","category":"gcp","subcategory":"gke","dateadded":"11-November-2025","certification":"","answerReference":"Limits the number of nodes that can be removed from a node pool in a single scale-down event.","answers":[{"text":"Limits the number of nodes that can be added in a single scale-up event.","iscorrect":false},{"text":"Limits the number of nodes that can be removed from a node pool in a single scale-down event.","iscorrect":true},{"text":"Limits the total number of nodes that can be removed over time.","iscorrect":false},{"text":"Limits the number of pods that can be removed from a node.","iscorrect":false}]},{"questionText":"What is the relationship between `PodPriority` and Cluster Autoscaler?","type":"","category":"gcp","subcategory":"gke","dateadded":"11-November-2025","certification":"","answerReference":"Higher priority pods are more likely to be scheduled, potentially triggering node scaling up sooner if resources are scarce.","answers":[{"text":"Lower priority pods are prioritized for scheduling, forcing scale-up.","iscorrect":false},{"text":"Higher priority pods are more likely to be scheduled, potentially triggering node scaling up sooner if resources are scarce.","iscorrect":true},{"text":"Pod priority directly controls node autoscaling limits.","iscorrect":false},{"text":"Pod priority has no effect on cluster autoscaling.","iscorrect":false}]},{"questionText":"What is the `autoscaling.kubernetes.io/recommendation` annotation?","type":"","category":"gcp","subcategory":"gke","dateadded":"11-November-2025","certification":"","answerReference":"Provided by the Vertical Pod Autoscaler, it suggests optimal resource requests and limits for pods.","answers":[{"text":"Used by Horizontal Pod Autoscaler to set target utilization.","iscorrect":false},{"text":"Provided by the Vertical Pod Autoscaler, it suggests optimal resource requests and limits for pods.","iscorrect":true},{"text":"Used by Cluster Autoscaler to recommend new node pool sizes.","iscorrect":false},{"text":"Indicates the current CPU usage of a pod.","iscorrect":false}]},{"questionText":"What are the common scaling challenges in GKE?","type":"","category":"gcp","subcategory":"gke","dateadded":"11-November-2025","certification":"","answerReference":"Setting appropriate resource requests/limits, configuring autoscalers correctly, and managing node pool configurations.","answers":[{"text":"Lack of monitoring tools.","iscorrect":false},{"text":"Setting appropriate resource requests/limits, configuring autoscalers correctly, and managing node pool configurations.","iscorrect":true},{"text":"Kubernetes not supporting auto-scaling.","iscorrect":false},{"text":"GKE control plane instability.","iscorrect":false}]},{"questionText":"What is the role of `terminationGracePeriodSeconds` in scaling down?","type":"","category":"gcp","subcategory":"gke","dateadded":"11-November-2025","certification":"","answerReference":"It defines how long a pod has to shut down gracefully when its node is being terminated or the pod is being evicted.","answers":[{"text":"It determines how quickly a node is added.","iscorrect":false},{"text":"It defines how long a pod has to shut down gracefully when its node is being terminated or the pod is being evicted.","iscorrect":true},{"text":"It sets the maximum time a pod can run.","iscorrect":false},{"text":"It specifies the number of replicas for a pod.","iscorrect":false}]},{"questionText":"How can you ensure that your applications scale effectively in GKE?","type":"","category":"gcp","subcategory":"gke","dateadded":"11-November-2025","certification":"","answerReference":"By properly defining resource requirements, configuring HPA and Cluster Autoscaler, and testing scaling behavior under load.","answers":[{"text":"By avoiding autoscaling and setting fixed replica counts.","iscorrect":false},{"text":"By properly defining resource requirements, configuring HPA and Cluster Autoscaler, and testing scaling behavior under load.","iscorrect":true},{"text":"By only using the default GKE autoscaling settings.","iscorrect":false},{"text":"By ensuring all nodes have the maximum possible resources.","iscorrect":false}]}]